fastly_client/__init__.py
fastly_client/models.py
fastly_client/schemas.py
fastly_client-0.1.7.dist-info/DESCRIPTION.rst
fastly_client-0.1.7.dist-info/METADATA
fastly_client-0.1.7.dist-info/RECORD
fastly_client-0.1.7.dist-info/WHEEL
fastly_client-0.1.7.dist-info/metadata.json
fastly_client-0.1.7.dist-info/top_level.txt
