Metadata-Version: 2.0
Name: fastly-client
Version: 0.1.7
Summary: Fastly API client that supports billing and stats.
Home-page: https://github.com/aryzhov/fastly-client
Author: Alexander Ryzhov
Author-email: aryzhov07@gmail.com
License: MIT
Keywords: fastly api billing stats client
Platform: UNKNOWN
Classifier: Development Status :: 3 - Alpha
Classifier: License :: OSI Approved :: MIT License
Classifier: Topic :: Software Development :: Libraries :: Python Modules
Classifier: Operating System :: OS Independent
Classifier: Programming Language :: Python :: 3
Requires-Dist: marshmallow (>=3.0.0b11)
Requires-Dist: requests (>=2.18.4)
